{
  "symbol": "NVDA",
  "timestamp": "2025-12-01T05:43:00.111505+00:00",
  "raw": {
    "yfinance": {
      "overview": {
        "marketCap": 4301985000000.0,
        "sharesOutstanding": null,
        "peRatio": null,
        "currency": "USD",
        "exchange": "NMS",
        "name": "NVIDIA Corporation",
        "sector": "Technology",
        "industry": "Semiconductors"
      },
      "balancesheet": {
        "totalAssets": 111601000000.0,
        "totalLiabilities": 32274000000.0,
        "shareholderEquity": 79327000000.0
      },
      "cashflow": {
        "operatingCashFlow": 64089000000.0,
        "freeCashFlow": 60853000000.0,
        "capitalExpenditures": null
      },
      "incomestatement": {
        "totalRevenue": 130497000000.0,
        "netIncome": 72880000000.0,
        "eps": null
      }
    },
    "finnhub": {
      "overview": {
        "name": "NVIDIA Corp",
        "currency": "USD",
        "exchange": "NASDAQ NMS - GLOBAL MARKET",
        "sector": "Semiconductors",
        "industry": "Semiconductors",
        "marketCap": 4301100000000000.0,
        "sharesOutstanding": 24300.0,
        "peRatio": 43.3587
      },
      "balancesheet": {
        "totalAssets": null,
        "totalLiabilities": null,
        "shareholderEquity": null
      },
      "cashflow": {
        "operatingCashFlow": null,
        "freeCashFlow": null,
        "capitalExpenditures": null
      },
      "incomestatement": {
        "totalRevenue": null,
        "netIncome": null,
        "eps": null
      }
    },
    "alphavantage": {
      "overview": {},
      "balancesheet": {
        "totalAssets": null,
        "totalLiabilities": null,
        "shareholderEquity": null
      },
      "cashflow": {
        "operatingCashFlow": null,
        "freeCashFlow": null,
        "capitalExpenditures": null
      },
      "incomestatement": {
        "totalRevenue": null,
        "netIncome": null,
        "eps": null
      }
    }
  }
}